fparser/.pylintrc
fparser/__init__.py
fparser/_version.py
fparser/api.py
fparser/conftest.py
fparser/common/__init__.py
fparser/common/base_classes.py
fparser/common/readfortran.py
fparser/common/sourceinfo.py
fparser/common/splitline.py
fparser/common/utils.py
fparser/common/tests/__init__.py
fparser/common/tests/conftest.py
fparser/common/tests/logging_utils.py
fparser/common/tests/modfile.f95
fparser/common/tests/test_base_classes.py
fparser/common/tests/test_readfortran.py
fparser/common/tests/test_sourceinfo.py
fparser/common/tests/test_splitline.py
fparser/common/tests/test_utils.py
fparser/common/tests/utf.f90
fparser/common/tests/utf_in_code.f90
fparser/one/__init__.py
fparser/one/block_statements.py
fparser/one/parsefortran.py
fparser/one/statements.py
fparser/one/typedecl_statements.py
fparser/one/tests/__init__.py
fparser/one/tests/bad_char.f90
fparser/one/tests/test_block_stmts.py
fparser/one/tests/test_do_block_r814.py
fparser/one/tests/test_parsefortran.py
fparser/one/tests/test_parser.py
fparser/one/tests/test_scripts.py
fparser/one/tests/test_select.py
fparser/one/tests/test_where_construct_stmt_r745.py
fparser/scripts/README.md
fparser/scripts/__init__.py
fparser/scripts/fparser2.py
fparser/scripts/fparser2_bench.py
fparser/scripts/parse.py
fparser/scripts/read.py
fparser/scripts/script_options.py
fparser/scripts/tests/test_fparser2_bench.py
fparser/scripts/tests/test_scripts.py
fparser/tests/funcfile.f95
fparser/tests/modfile.f95
fparser/tests/test_api.py
fparser/tests/test_blank_lines.py
fparser/tests/test_comment.py
fparser/tests/test_f90comment_f77source.py
fparser/tests/test_fparser_module.py
fparser/tests/test_functional.py
fparser/tests/test_issue10.py
fparser/tests/test_issue11.py
fparser/tests/test_issue23.py
fparser/tests/test_issue25.py
fparser/tests/test_issue26.py
fparser/tests/test_issue33.py
fparser/tests/test_issue4.py
fparser/tests/test_issue5.py
fparser/tests/test_issue7.py
fparser/tests/test_issue8.py
fparser/tests/test_issue9.py
fparser-0.2.1.dist-info/licenses/LICENSE
fparser-0.2.1.dist-info/METADATA
fparser-0.2.1.dist-info/WHEEL
fparser-0.2.1.dist-info/entry_points.txt
fparser-0.2.1.dist-info/top_level.txt
fparser-0.2.1.dist-info/RECORD
