Metadata-Version: 2.4
Name: fparser
Version: 0.2.1
Summary: Python implementation of a Fortran parser
Author: Pearu Peterson, Rupert Ford
Author-email: Andrew Porter <andrew.porter@stfc.ac.uk>
License: BSD-3-Clause
Keywords: fortran,parser
Classifier: Development Status :: 4 - Beta
Classifier: Environment :: Console
Classifier: Intended Audience :: Developers
Classifier: Intended Audience :: Science/Research
Classifier: Natural Language :: English
Classifier: Programming Language :: Fortran
Classifier: Programming Language :: Python
Classifier: Topic :: Scientific/Engineering
Classifier: Topic :: Software Development
Classifier: Topic :: Utilities
Classifier: Operating System :: POSIX
Classifier: Operating System :: Unix
Classifier: Operating System :: MacOS
Requires-Python: >=3.6
License-File: LICENSE
Requires-Dist: setuptools_scm
Provides-Extra: doc
Requires-Dist: sphinx; extra == "doc"
Requires-Dist: sphinxcontrib.bibtex; extra == "doc"
Requires-Dist: autoapi; extra == "doc"
Requires-Dist: sphinx-autoapi; extra == "doc"
Requires-Dist: sphinx_rtd_theme; extra == "doc"
Provides-Extra: tests
Requires-Dist: pytest>=3.3.0; extra == "tests"
Dynamic: license-file
